social_auth_mitxpro/__init__.py
social_auth_mitxpro/backends.py
social_auth_mitxpro/backends_test.py
social_auth_mitxpro/conftest.py
social_auth_mitxpro-0.7.1.dist-info/LICENSE
social_auth_mitxpro-0.7.1.dist-info/METADATA
social_auth_mitxpro-0.7.1.dist-info/WHEEL
social_auth_mitxpro-0.7.1.dist-info/RECORD
