Metadata-Version: 2.1
Name: social-auth-mitxpro
Version: 0.7.1
Summary: python-social-auth backend for mitxpro
Home-page: https://pypi.org/project/social-auth-mitxpro
License: MIT
Author: MIT Office of Open Learning
Author-email: mitx-devops@mit.edu
Requires-Python: >=3.8
Classifier: License :: OSI Approved :: MIT License
Classifier: Natural Language :: English
Classifier: Operating System :: OS Independent
Classifier: Programming Language :: Python
Classifier: Programming Language :: Python :: 3
Classifier: Programming Language :: Python :: 3.8
Classifier: Programming Language :: Python :: 3.9
Classifier: Programming Language :: Python :: 3.10
Classifier: Programming Language :: Python :: 3.11
Classifier: Programming Language :: Python :: 3.12
Requires-Dist: attrs (>=24.0.0,<25.0.0)
Requires-Dist: social-auth-core (>=4.1.0,<5.0.0)
Project-URL: Repository, https://github.com/mitodl/social-auth-mitxpro/
